odoo/addons/stock_orderpoint_mrp_link/README.rst
odoo/addons/stock_orderpoint_mrp_link/__init__.py
odoo/addons/stock_orderpoint_mrp_link/__manifest__.py
odoo/addons/stock_orderpoint_mrp_link/i18n/fr.po
odoo/addons/stock_orderpoint_mrp_link/i18n/stock_orderpoint_mrp_link.pot
odoo/addons/stock_orderpoint_mrp_link/i18n/zh_CN.po
odoo/addons/stock_orderpoint_mrp_link/models/__init__.py
odoo/addons/stock_orderpoint_mrp_link/models/mrp_production.py
odoo/addons/stock_orderpoint_mrp_link/models/stock_rule.py
odoo/addons/stock_orderpoint_mrp_link/models/stock_warehouse_orderpoint.py
odoo/addons/stock_orderpoint_mrp_link/readme/CONTRIBUTORS.rst
odoo/addons/stock_orderpoint_mrp_link/readme/DESCRIPTION.rst
odoo/addons/stock_orderpoint_mrp_link/static/description/icon.png
odoo/addons/stock_orderpoint_mrp_link/static/description/index.html
odoo/addons/stock_orderpoint_mrp_link/tests/__init__.py
odoo/addons/stock_orderpoint_mrp_link/tests/test_stock_orderpoint_mrp_link.py
odoo/addons/stock_orderpoint_mrp_link/views/stock_orderpoint_views.xml
odoo12_addon_stock_orderpoint_mrp_link-12.0.1.0.0.99.dev9.dist-info/METADATA
odoo12_addon_stock_orderpoint_mrp_link-12.0.1.0.0.99.dev9.dist-info/WHEEL
odoo12_addon_stock_orderpoint_mrp_link-12.0.1.0.0.99.dev9.dist-info/top_level.txt
odoo12_addon_stock_orderpoint_mrp_link-12.0.1.0.0.99.dev9.dist-info/RECORD
